virtomate/__init__.py
virtomate/__main__.py
virtomate/domain.py
virtomate/error.py
virtomate/guest.py
virtomate/pool.py
virtomate/volume.py
virtomate-0.1.2.dist-info/METADATA
virtomate-0.1.2.dist-info/WHEEL
virtomate-0.1.2.dist-info/entry_points.txt
virtomate-0.1.2.dist-info/licenses/LICENSE.txt
virtomate-0.1.2.dist-info/RECORD
