Metadata-Version: 2.4
Name: virtomate
Version: 0.1.2
Summary: A scripting-friendly tool to manage virtual machines with libvirt.
Project-URL: Homepage, https://virtomate.org/
Project-URL: Documentation, https://virtomate.org/
Project-URL: Repository, https://github.com/aahlenst/virtomate
Author-email: Andreas Ahlenstorf <andreas@ahlenstorf.ch>
License-File: LICENSE.txt
Classifier: Development Status :: 4 - Beta
Classifier: Environment :: Console
Classifier: Intended Audience :: Developers
Classifier: Intended Audience :: System Administrators
Classifier: License :: OSI Approved :: GNU General Public License v2 (GPLv2)
Classifier: Operating System :: POSIX :: Linux
Classifier: Programming Language :: Python :: 3
Requires-Python: >=3.10
Requires-Dist: libvirt-python>=9.0.0
